maple/__init__.py
maple/base_extensions.py
maple/models.py
maple/ops.py
maple/report.py
maple/utils.py
maple/templates/report.html
maple_spec-0.1.5.dist-info/licenses/LICENSE
maple_spec-0.1.5.dist-info/METADATA
maple_spec-0.1.5.dist-info/WHEEL
maple_spec-0.1.5.dist-info/top_level.txt
maple_spec-0.1.5.dist-info/RECORD
