Metadata-Version: 2.4
Name: maple-spec
Version: 0.1.5
Summary: A testing library for Speckle models
Author-email: Gizem Demirhan <gizemdemirhaan@gmail.com>, Andres Buitrago <andrsbtrg@gmail.com>
Project-URL: Homepage, https://github.com/andrsbtrg/maple
Project-URL: Issues, https://github.com/andrsbtrg/maple/issues
Classifier: Development Status :: 4 - Beta
Classifier: Programming Language :: Python :: 3
Classifier: License :: OSI Approved :: Apache Software License
Classifier: Operating System :: OS Independent
Requires-Python: >=3.8
License-File: LICENSE
Requires-Dist: specklepy>=3
Requires-Dist: importlib-metadata
Requires-Dist: jinja2
Requires-Dist: python-dotenv
Requires-Dist: acers
Dynamic: license-file
